cidr_bottle/__init__.py
cidr_bottle/cidr_bottle.py
cidr_bottle/cidr_bottle_fast.py
cidr_bottle-1.5.3.dist-info/LICENSE
cidr_bottle-1.5.3.dist-info/METADATA
cidr_bottle-1.5.3.dist-info/WHEEL
cidr_bottle-1.5.3.dist-info/RECORD
