Metadata-Version: 2.3
Name: CIDR-Bottle
Version: 1.5.3
Summary: CIDR-Bottle is yet another Patricia Trie implementation, however this one is specifically designed for parsing and validating CIDRS in routing tables and ROAs.
License: MIT
Keywords: cidr,routing,patricia,IPv6,IPv4,ROA,cidr-trie
Author: Tim Armstrong
Author-email: tim@plaintextnerds.com
Maintainer: Tim Armstrong
Maintainer-email: tim@plaintextnerds.com
Requires-Python: >=3.8,<3.15
Classifier: Intended Audience :: Telecommunications Industry
Classifier: License :: OSI Approved :: MIT License
Classifier: Programming Language :: Python :: 3
Classifier: Programming Language :: Python :: 3.8
Classifier: Programming Language :: Python :: 3.9
Classifier: Programming Language :: Python :: 3.10
Classifier: Programming Language :: Python :: 3.11
Classifier: Programming Language :: Python :: 3.12
Classifier: Programming Language :: Python :: 3.13
Classifier: Programming Language :: Python :: Implementation
Classifier: Topic :: Internet
Classifier: Topic :: Software Development :: Libraries
Classifier: Topic :: Software Development :: Libraries :: Python Modules
Classifier: Topic :: System :: Networking
Classifier: Topic :: System :: Networking :: Firewalls
Requires-Dist: cidr-man (>=1.5.4,<2.0.0)
Project-URL: Homepage, https://geoip.network/
Project-URL: Repository, https://gitlab.com/geoip.network/cidr_bottle
